wav2samp/__init__.py
wav2samp-0.2.dist-info/LICENSE.txt
wav2samp-0.2.dist-info/METADATA
wav2samp-0.2.dist-info/WHEEL
wav2samp-0.2.dist-info/top_level.txt
wav2samp-0.2.dist-info/RECORD
